docs/conf.py
xPDFsim/main.py
xPDFsim/pdf.py
xPDFsim/utils.py
xpdfsim-0.0.3.dist-info/licenses/LICENSE
xpdfsim-0.0.3.dist-info/METADATA
xpdfsim-0.0.3.dist-info/WHEEL
xpdfsim-0.0.3.dist-info/entry_points.txt
xpdfsim-0.0.3.dist-info/top_level.txt
xpdfsim-0.0.3.dist-info/RECORD
