Metadata-Version: 2.4
Name: xPDFsim
Version: 0.0.3
Summary: Simple simulation of X-ray pair distribution functions.
Author: Jan-Benedikt Weiß
License-Expression: GPL-3.0-or-later
Project-URL: Repository, https://github.com/JBWeiss-chem/xPDFsim
Project-URL: Documentation, https://xpdfsim.readthedocs.io
Keywords: xPDF,disordered materials,simulation,crystallography,scattering,X-ray
Classifier: Development Status :: 3 - Alpha
Classifier: Intended Audience :: Science/Research
Classifier: Programming Language :: Python
Classifier: Operating System :: OS Independent
Requires-Python: >=3.8
License-File: LICENSE
Requires-Dist: numpy
Requires-Dist: scipy
Requires-Dist: pymatgen
Requires-Dist: pandas
Requires-Dist: bokeh
Dynamic: license-file
